{
  "id": "ramadan-sahar-dua-ya-uddati",
  "title": "Dua Ya Uddati - Dua for sahar time (commencing the fast)",
  "featured": false,
  "relatedLinks": [
    {
      "text": "PDF",
      "url": "https://www.duas.org/pdfs/Dua%20Ya%20Uddati%20-%20linebyline%20-%20duas.org.pdf"
    }
  ],
  "duas": [
    {
      "type": "dua",
      "id": "dua-1",
      "title": "Dua Ya Uddati - Dua-e-Sahar",
      "description": "Shaykh al-Tusi has mentioned the following supplication to be said at the last hours of the Month of Ramadan nights (Time of Suhoor):",
      "segments": [
        {
          "arabic": "يَا عُدَّتِي فِي كُرْبَتِي",
          "transliteration": "ya `uddati fi kurbati",
          "translation": "O my means in troubles!"
        },
        {
          "arabic": "وَيَا صَاحِبِي فِي شِدَّتِي",
          "transliteration": "wa ya sahibi fi shiddati",
          "translation": "O my Companion in hardships!"
        },
        {
          "arabic": "وَيَا وَلِيِّي فِي نِعْمَتِي",
          "transliteration": "wa ya waliyyi fi ni`mati",
          "translation": "O the Provider of my amenities!"
        },
        {
          "arabic": "وَيَا غَايَتِي فِي رَغْبَتِي",
          "transliteration": "wa ya ghayati fi raghbati",
          "translation": "O the utmost of my desires!"
        },
        {
          "arabic": "أَنْتَ ٱلسَّاتِرُ عَوْرَتِي",
          "transliteration": "anta alssatiru `awrati",
          "translation": "It is You Who conceals my defects,"
        },
        {
          "arabic": "وَٱلْمُؤْمِنُ رَوْعَتِي",
          "transliteration": "walmu'minu raw`ati",
          "translation": "relieves my apprehensions,"
        },
        {
          "arabic": "وَٱلْمُقِيلُ عَثْرَتِي",
          "transliteration": "walmuqilu `athrati",
          "translation": "and overlooks my slips."
        },
        {
          "arabic": "فَٱغْفِرْ لِي خَطِيئَتِي",
          "transliteration": "faghfir li khati'ati",
          "translation": "So, (please do) forgive my sin."
        },
        {
          "arabic": "اَللَّهُمَّ إِنِّي أَسْأَلُكَ خُشُوعَ ٱلإِيـمَانِ",
          "transliteration": "allahumma inni as'aluka khushu`a al'imani",
          "translation": "O Allah, I pray You for the submission of faith"
        },
        {
          "arabic": "قَبْلَ خُشُوعِ ٱلذُلَّ فِي ٱلنَّارِ",
          "transliteration": "qabla khushu`i aldhulli fi alnnari",
          "translation": "before I encounter the submission of humiliation in Hellfire."
        },
        {
          "arabic": "يَا وَاحِدُ يَا أَحَدُ يَا صَمَدُ",
          "transliteration": "ya wahidu ya ahadu ya samadu",
          "translation": "O One!: O Absolute! O Besought of all!"
        },
        {
          "arabic": "يَا مَنْ لَمْ يَلِدْ وَلَمْ يُولَدْ",
          "transliteration": "ya man lam yalid wa lam yulad",
          "translation": "O He Who neither begets nor is He begotten,"
        },
        {
          "arabic": "وَلَمْ يَكُنْ لَهُ كُفُواً أَحَدٌ",
          "transliteration": "wa lam yakun lahu kufwan ahadun",
          "translation": "and there is none like to Him"
        },
        {
          "arabic": "يَا مَنْ يُعْطِي مَنْ سَأَلَهُ",
          "transliteration": "ya man yu`ti man sa'alahu",
          "translation": "O He Who confers upon one who beseeches Him"
        },
        {
          "arabic": "تَحَنُّناً مِنْهُ وَرَحْمَةً",
          "transliteration": "tahannunan minhu wa rahmatan",
          "translation": "on account of His sympathy and mercy,"
        },
        {
          "arabic": "وَيَبْتَدِئُ بِٱلْخَيْرِ مَنْ لَمْ يَسْأَلْهُ",
          "transliteration": "wa yabtadi'u bilkhayri man lam yas'alhu",
          "translation": "and initially grants welfare to those who have not asked for it,"
        },
        {
          "arabic": "تَفَضُّلاً مِنْهُ وَكَرَماً",
          "transliteration": "tafaddulan minhu wa karaman",
          "translation": "on account of His liberality and generosity!"
        },
        {
          "arabic": "بِكَرَمِكَ ٱلدَّائِمِ",
          "transliteration": "bikaramika aldda'imi",
          "translation": "I beseech You in the name of Your endless generosity"
        },
        {
          "arabic": "صَلِّ عَلَىٰ مُحَمَّدٍ وَآلِ مُحَمَّدٍ",
          "transliteration": "salli `ala muhammadin wa ali muhammadin",
          "translation": "to bless Muhammad and the Household of Muhammad"
        },
        {
          "arabic": "وَهَبْ لِي رَحْمَةً وَاسِعَةً جَامِعَةً",
          "transliteration": "wa hab li rahmatan wasi`atan jami`atan",
          "translation": "and bestow upon me with mercy—vast and comprehensive—"
        },
        {
          "arabic": "أَبْلُغُ بِهَا خَيْرَ ٱلدُّنْيَا وَٱلآخِرَةِ",
          "transliteration": "ablughu biha khayra alddunya wal-akhirati",
          "translation": "by which I can win the welfare of this world as well as the Next World."
        },
        {
          "arabic": "اَللَّهُمَّ إِنِّي أَسْتَغْفِرُكَ لِمَا تُبْتُ إِلَيْكَ مِنْهُ ثُمَّ عُدْتُ فِيهِ",
          "transliteration": "allahumma inni astaghfiruka lima tubtu ilayka minhu thumm `udtu fihi",
          "translation": "O Allah, I implore for Your forgiveness of the sins from which I had repented to You but I committed them again."
        },
        {
          "arabic": "وَأَسْتَغْفِرُكَ لِكُلِّ خَيْرٍ أَرَدْتُ بِهِ وَجْهَكَ",
          "transliteration": "wa astaghfiruka likulli khayrin aradtu bihi wajhaka",
          "translation": "I implore for Your forgiveness of my righteous acts that although I intended them purely for Your sake,"
        },
        {
          "arabic": "فَخَالَطَنِي فِيهِ مَا لَيْسَ لَكَ",
          "transliteration": "fakhalatani fihi ma laysa laka",
          "translation": "some purposes that are not intended for You intruded upon them."
        },
        {
          "arabic": "اَللَّهُمَّ صَلِّ عَلَىٰ مُحَمَّدٍ وَآلِ مُحَمَّدٍ",
          "transliteration": "allahumma salli `ala muhammadin wa ali muhammadin",
          "translation": "O Allah, (please do) send blessings to Muhammad and the Household of Muhammad"
        },
        {
          "arabic": "وَٱعْفُ عَنْ ظُلْمِي وَجُرْمِي",
          "transliteration": "wa`fu `an zulmi wa jurmi",
          "translation": "and pardon my transgression and my offenses,"
        },
        {
          "arabic": "بِحِلْمِكَ وَجُودِكَ يَا كَرِيمُ",
          "transliteration": "bihilmika wa judika ya karimu",
          "translation": "in the name of Your forbearance and magnanimity. O All-generous!"
        },
        {
          "arabic": "يَا مَنْ لاَ يَخِيبُ سَائِلُهُ",
          "transliteration": "ya man la yakhibu sa'iluhu",
          "translation": "O He Whose beseecher will never be disappointed!"
        },
        {
          "arabic": "وَلاَ يَنْفَدُ نَائِلُهُ",
          "transliteration": "wa la yanfadu na'iluhu",
          "translation": "O He Whose His rewards will never run out!"
        },
        {
          "arabic": "يَا مَنْ عَلاَ فَلاَ شَيْءَ فَوْقَهُ",
          "transliteration": "ya man `ala fala shay'a fawqahu",
          "translation": "O He Who is so Elevated that nothing can ever be higher than He is"
        },
        {
          "arabic": "وَدَنَا فَلاَ شَيْءَ دُونَهُ",
          "transliteration": "wa dana fala shay'a dunahu",
          "translation": "and Who is so Nigh that nothing can ever be closer that He is!"
        },
        {
          "arabic": "صَلِّ عَلَىٰ مُحَمَّدٍ وَآلِ مُحَمَّدٍ",
          "transliteration": "salli `ala muhammadin wa ali muhammadin",
          "translation": "(Please do) send blessings to Muhammad and the Household of Muhammad"
        },
        {
          "arabic": "وَٱرْحَمْنِي",
          "transliteration": "warhamni",
          "translation": "and have mercy upon me,"
        },
        {
          "arabic": "يَا فَالِقَ ٱلْبَحْرِ لِمُوسَىٰ",
          "transliteration": "ya faliqa albahri limusa",
          "translation": "O He Who split asunder the sea for (Prophet) Moses,"
        },
        {
          "arabic": "ٱللَّيْلَةَ ٱللَّيْلَةَ ٱللَّيْلَةَ",
          "transliteration": "allaylata allaylata allaylata",
          "translation": "this very night, this very night, this very night,"
        },
        {
          "arabic": "ٱلسَّاعَةَ ٱلسَّاعَةَ ٱلسَّاعَةَ",
          "transliteration": "alssa`ata alssa`ata alssa`ata",
          "translation": "this very hour, this very hour, this very hour."
        },
        {
          "arabic": "اَللَّهُمَّ طَهِّرْ قَلْبِي مِنَ ٱلنِّفَاقِ",
          "transliteration": "allahumma tahhir qalbi min alnnifaqi",
          "translation": "O Allah, (please do) purify my heart from hypocrisy,"
        },
        {
          "arabic": "وَعَمَلِي مِنَ ٱلرِّيَاءِ",
          "transliteration": "wa `amali min alrriya'i",
          "translation": "my acts from showing off,"
        },
        {
          "arabic": "وَلِسَانِي مِنَ ٱلكَذِبِ",
          "transliteration": "wa lisani min alkadhibi",
          "translation": "my tongue from telling untruths,"
        },
        {
          "arabic": "وَعَيْنِي مِنَ ٱلْخِيَانَةِ",
          "transliteration": "wa `ayni min alkhiyanati",
          "translation": "and my eye from treason."
        },
        {
          "arabic": "فَإِنَّكَ تَعْلَمُ خَائِنَةَ ٱلأَعْيُنِ وَمَا تُخْفِي ٱلصُّدُورُ",
          "transliteration": "fa'innaka ta`lamu kha'inata al-a`yuni wa ma tukhfi alssuduru",
          "translation": "You verily know the stealthy looks and that which the breasts conceal."
        },
        {
          "arabic": "يَا رَبِّ هٰذَا مَقَامُ ٱلْعَائِذِ بِكَ مِنَ ٱلنَّارِ",
          "transliteration": "ya rabbi hadha maqamu al`a'idhi bika min alnnari",
          "translation": "O my Lord, this is the manner of him who seeks Your protection from Hellfire."
        },
        {
          "arabic": "هٰذَا مَقَامُ ٱلْمُسْتَجِيرِ بِكَ مِنَ ٱلنَّارِ",
          "transliteration": "hadha maqamu almustajiri bika min alnnari",
          "translation": "This is the manner of him who seeks Your shelter against Hellfire."
        },
        {
          "arabic": "هٰذَا مَقَامُ ٱلْمُسْتَغِيثِ بِكَ مِنَ ٱلنَّارِ",
          "transliteration": "hadha maqamu almustaghithi bika min alnnari",
          "translation": "This is the manner of him who seeks Your aid against Hellfire."
        },
        {
          "arabic": "هٰذَا مَقَامُ ٱلْهَارِبِ إِلَيْكَ مِنَ ٱلنَّارِ",
          "transliteration": "hadha maqamu alharibi ilayka min alnnari",
          "translation": "This is the manner of him who flees to You from Hellfire."
        },
        {
          "arabic": "هٰذَا مَقَامُ مَنْ يَبُوءُ لَكَ بِخَطِيئَتِهِ",
          "transliteration": "hadha maqamu man yabu'u laka bikhati'atihi",
          "translation": "This is the manner of him who returns to You carrying his offenses,"
        },
        {
          "arabic": "وَيَعْتَرِفُ بِذَنْبِهِ",
          "transliteration": "wa ya`tarifu bidhanbihi",
          "translation": "confessing of his sins,"
        },
        {
          "arabic": "وَيَتُوبُ إِلَىٰ رَبِّهِ",
          "transliteration": "wa yatubu ila rabbihi",
          "translation": "and repenting to You—his Lord."
        },
        {
          "arabic": "هٰذَا مَقَامُ ٱلْبَائِسِ ٱلْفَقِيرِ",
          "transliteration": "hadha maqamu alba'isi alfaqiri",
          "translation": "This is the manner of the miserable and poor."
        },
        {
          "arabic": "هٰذَا مَقَامُ ٱلْخَائِفِ ٱلْمُسْتَجِيرِ",
          "transliteration": "hadha maqamu alkha'ifi almustajiri",
          "translation": "This is the manner of the fearful and seeker of Your refuge."
        },
        {
          "arabic": "هٰذَا مَقَامُ ٱلْمَحْزُونِ ٱلْمَكْرُوبِ",
          "transliteration": "hadha maqamu almahzuni almakrubi",
          "translation": "This is the manner of the aggrieved and distressed."
        },
        {
          "arabic": "هٰذَا مَقَامُ ٱلْمَغْمُومِ ٱلْمَهْمُومِ",
          "transliteration": "hadha maqamu almaghmumi almahmumi",
          "translation": "This is the manner of the depressing and gloomy."
        },
        {
          "arabic": "هٰذَا مَقَامُ ٱلْغَرِيبِ ٱلْغَرِيقِ",
          "transliteration": "hadha maqamu algharibi alghariqi",
          "translation": "This is the manner of the stranger and drowned."
        },
        {
          "arabic": "هٰذَا مَقَامُ ٱلْمُسْتَوْحِشِ ٱلْفَرِقِ",
          "transliteration": "hadha maqamu almustawhishi alfariqi",
          "translation": "This is the manner of the alienated and frightened."
        },
        {
          "arabic": "هٰذَا مَقَامُ مَنْ لاَ يَجِدُ لِذَنْبِهِ غَافِراً غَيْرَكَ",
          "transliteration": "hadha maqamu man la yajidu lidhanbihi ghafiran ghayraka",
          "translation": "This is the manner of him who cannot find anyone save You to forgive his sins,"
        },
        {
          "arabic": "وَلاَ لِضَعْفِهِ مُقَوِّياً إِلاَّ أَنْتَ",
          "transliteration": "wa la lida`fihi muqawiyyan illa anta",
          "translation": "who cannot find anyone save You to give him power,"
        },
        {
          "arabic": "وَلاَ لِهَمِّهِ مُفَرِّجاً سِوَاكَ",
          "transliteration": "wa la lihammihi mufarrijan siwaka",
          "translation": "and who cannot find anyone save You to relieve his grief."
        },
        {
          "arabic": "يَا اللَّهُ يَا كَرِيمُ",
          "transliteration": "ya allahu ya karimu",
          "translation": "O Allah! O All-generous!"
        },
        {
          "arabic": "لاَ تُحْرِقْ وَجْهِي بِٱلنَّارِ بَعْدَ سُجُودِي لَكَ وَتَعْفِيرِي",
          "transliteration": "la tuhriq wajhi bilnnari ba`da sujudi laka wa ta`firi",
          "translation": "(please) do not burn my face with Hellfire after I have prostrated myself before You and I have soiled my face for You."
        },
        {
          "arabic": "بِغَيرِ مَنٍّ مِنِّي عَلَيْكَ",
          "transliteration": "bighayri mannin minni `alayka",
          "translation": "Of course, this is not a personal favor that I have done to myself;"
        },
        {
          "arabic": "بَلْ لَكَ ٱلْحَمْدُ وَٱلْمَنُّ وَٱلتَّفَضُّلُ عَلَيَّ",
          "transliteration": "bal laka alhamdu walmannu walttafaddulu `alayya",
          "translation": "rather, it is on account of Your praiseworthy favor to and guidance of me."
        },
        {
          "arabic": "إِرْحَمْ أَيْ رَبِّ أَيْ رَبِّ أَيْ رَبِّ",
          "transliteration": "irham ay rabbi ay rabbi ay rabbi…",
          "translation": "So, have mercy, O Lord! O Lord! O Lord…"
        },
        {
          "arabic": "ضَعْفِي",
          "transliteration": "da`fi",
          "translation": "upon my weakness,"
        },
        {
          "arabic": "وَقِلَّةَ حِيلَتِي",
          "transliteration": "wa qillata hilati",
          "translation": "upon my confusedness,"
        },
        {
          "arabic": "وَرِقَّةَ جِلْدِي",
          "transliteration": "wa riqqata jildi",
          "translation": "upon the softness of my skin,"
        },
        {
          "arabic": "وَتَبَدُّدَ أَوْصَالِي",
          "transliteration": "wa tabadduda awsali",
          "translation": "upon the separation of my organs,"
        },
        {
          "arabic": "وَتَنَاثُرَ لَحْمِي وَجِسْمِي وَجَسَدِي",
          "transliteration": "wa tanathura lahmi wa jismi wa jasadi",
          "translation": "upon the dispersal of my flesh, body, and corpse,"
        },
        {
          "arabic": "وَوَحْدَتِي وَوَحْشَتِي فِي قَبْرِي",
          "transliteration": "wa wahdati wa wahshati fi qabri",
          "translation": "upon my loneliness and lonesomeness in my grave,"
        },
        {
          "arabic": "وَجَزَعِي مِنْ صَغِيرِ ٱلْبَلاَءِ",
          "transliteration": "wa jaza`i min saghiri albala'i",
          "translation": "and upon my anxiety at the least misfortune that inflicts me."
        },
        {
          "arabic": "أَسْأَلُكَ يَا رَبِّ قُرَّةَ ٱلْعَيْنِ وَٱلاِغْتِبَاطَ",
          "transliteration": "as'aluka ya rabbi qurrata al`ayni walightibata",
          "translation": "I beseech You, O Lord, for delight and happiness"
        },
        {
          "arabic": "يَوْمَ ٱلْحَسْرَةِ وَٱلنَّدَامَةِ",
          "transliteration": "yawma alhasrati walnnadamati",
          "translation": "on the Day of regret and remorse."
        },
        {
          "arabic": "بَيِّضْ وَجْهِي يَا رَبِّ يَوْمَ تَسْوَدُّ ٱلْوُجُوهُ",
          "transliteration": "bayyid wajhi ya rabbi yawma taswaddu alwujuhu",
          "translation": "(Please do) whiten my face, O Lord, when some faces will be blackened."
        },
        {
          "arabic": "آمِنِّي مِنَ ٱلْفَزَعِ ٱلأَكْبَرِ",
          "transliteration": "aminni min alfaza`i al-akbari",
          "translation": "(Please do) secure me against the Gravest Horror."
        },
        {
          "arabic": "أَسْأَلُكَ ٱلْبُشْرَىٰ يَوْمَ تُقَلَّبُ ٱلْقُلُوبُ وَٱلأَبْصَارُ",
          "transliteration": "as'aluka albushra yawma tuqallabu alqulubu wal-absaru",
          "translation": "I beseech You for good tidings when hearts and sights shall be turned about"
        },
        {
          "arabic": "وَٱلْبُشْرَىٰ عِنْدَ فِرَاقِ ٱلدُّنْيَا",
          "transliteration": "walbushra `inda firaqi alddunya",
          "translation": "and for good tidings when I depart this life."
        },
        {
          "arabic": "الْحَمْدُ لِلَّهِ ٱلَّذِي أَرْجُوهُ عَوْناً لِي فِي حَيَاتِي",
          "transliteration": "alhamdu lillahi alladhi arjuhu `awnan li fi hayati",
          "translation": "All praise be to Allah Whom I hope for supporting me in my life"
        },
        {
          "arabic": "وَأُعِدُّهُ ذُخْراً لِيَوْمِ فَاقَتِي",
          "transliteration": "wa u`idduhu dhukhran liyawmi faqati",
          "translation": "and Whom I want to act as my Provision on the day of my neediness."
        },
        {
          "arabic": "الْحَمْدُ لِلَّهِ ٱلَّذِي أَدْعُوهُ وَلاَ أَدْعُو غَيْرَهُ",
          "transliteration": "alhamdu lillahi alladhi ad`uhu wa la ad`u ghayrahu",
          "translation": "All praise be to Allah Whom alone do I beseech and I never beseech anyone rather than Him;"
        },
        {
          "arabic": "وَلَوْ دَعَوْتُ غَيْرَهُ لَخَيَّبَ دُعَائِي",
          "transliteration": "wa law da`awtu ghayrahu lakhayyaba du`a'i",
          "translation": "and even if I beseech anyone else, he will definitely let me down."
        },
        {
          "arabic": "الْحَمْدُ لِلَّهِ ٱلَّذِي أَرْجُوهُ وَلاَ أَرْجُو غَيْرَهُ",
          "transliteration": "alhamdu lillahi alladhi arjuhu wa la arju ghayrahu",
          "translation": "All praise be to Allah for Whom I hope and I never hope for anyone rather than Him;"
        },
        {
          "arabic": "وَلَوْ رَجَوْتُ غَيْرَهُ َلأَخْلَفَ رَجَائِي",
          "transliteration": "wa law rajawtu ghayrahu la-akhlafa raja'i",
          "translation": "and even if I hope for anyone else, he will definitely disappoint me."
        },
        {
          "arabic": "الْحَمْدُ لِلَّهِ ٱلْمُنْعِمِ ٱلْمُحْسِنِ",
          "transliteration": "alhamdu lillahi almun`imi almuhsini",
          "translation": "All praise be to Allah, the All-benefactor, the All-donor,"
        },
        {
          "arabic": "ٱلْمُجْمِلِ ٱلْمُفْضِلِ",
          "transliteration": "almujmili almufdili",
          "translation": "the All-favorer, the All-liberal,"
        },
        {
          "arabic": "ذِي ٱلْجَلالِ وَٱلإِكْرَامِ",
          "transliteration": "dhi aljalali wal-ikrami",
          "translation": "the Lord of Majesty and Honor,"
        },
        {
          "arabic": "وَلِيُّ كُلِّ نِعْمَةٍ",
          "transliteration": "waliyyu kulli ni`matin",
          "translation": "the Source of all bounties,"
        },
        {
          "arabic": "وَصَاحِبُ كُلِّ حَسَنَةٍ",
          "transliteration": "wa sahibu kulli hasanatin",
          "translation": "the Cause of all good deeds,"
        },
        {
          "arabic": "وَمُنْتَهَىٰ كُلِّ رَغْبَةٍ",
          "transliteration": "wa muntaha kulli raghbatin",
          "translation": "the Ultimate Goal of all desires,"
        },
        {
          "arabic": "وَقَاضِي كُلِّ حَاجَةٍ",
          "transliteration": "wa qadi kulli hajatin",
          "translation": "and the Answerer of all needs."
        },
        {
          "arabic": "اَللَّهُمَّ صَلِّ عَلَىٰ مُحَمَّدٍ وَآلِ مُحَمَّدٍ",
          "transliteration": "allahumma salli `ala muhammadin wa ali muhammadin",
          "translation": "O Allah, (please do) send blessings to Muhammad and the Household of Muhammad"
        },
        {
          "arabic": "وَٱرْزُقْنِي ٱلْيَقِينَ وَحُسْنَ ٱلظَّنِّ بِكَ",
          "transliteration": "warzuqni alyaqina wa husna alzzanni bika",
          "translation": "and grant me conviction and having good idea about You,"
        },
        {
          "arabic": "وَأَثْبِتْ رَجَاءَكَ فِي قَلْبِي",
          "transliteration": "wa athbit raja'aka fi qalbi",
          "translation": "fix my hope for You in my heart,"
        },
        {
          "arabic": "وَٱقْطَعْ رَجَائِي عَمَّنْ سِوَاكَ",
          "transliteration": "waqta` raja'i `amman siwaka",
          "translation": "and deprive me of putting my hope in anyone other than You,"
        },
        {
          "arabic": "حَتَّىٰ لاَ أَرْجُوَ غَيْرَكَ وَلاَ أَثِقَ إِلاَّ بِكَ",
          "transliteration": "hatta la arjwa ghayraka wa la athiqa illa bika",
          "translation": "so that I shall hope for none but You and I shall trust none but You."
        },
        {
          "arabic": "يَا لَطِيفاً لِمَا تَشَاءُ",
          "transliteration": "ya latifan lima tasha'u",
          "translation": "O He Who is Benignant to whom He pleases!"
        },
        {
          "arabic": "أُلْطُفْ لِي فِي جَمِيعِ أَحْوَالِي بِمَا تُحِبُّ وَتَرْضَىٰ",
          "transliteration": "ultuf li fi jami`i ahwali bima tuhibbu wa tarda",
          "translation": "(Please do) have benignity to me in all my manners in the very way that You like and please."
        },
        {
          "arabic": "يَا رَبِّ إِنِّي ضَعِيفٌ عَلَىٰ ٱلنَّارِ فَلاَ تُعَذِّبْنِي بِٱلنَّارِ",
          "transliteration": "ya rabbi inni da`ifun `ala alnnari fala tu`adhdhibni bilnnari",
          "translation": "O my Lord, I am too weak to encounter Your Fire; therefore, (please) do not punish me with Your Fire."
        },
        {
          "arabic": "يَا رَبِّ ٱرْحَمْ دُعَائِي وَتَضَرُّعِي",
          "transliteration": "ya rabbi irham du`a'i wa tadarru`i",
          "translation": "O my Lord, (please do) have mercy upon my prayers, my earnest imploring,"
        },
        {
          "arabic": "وَخَوْفِي وَذُلِّي وَمَسْكَنَتِي",
          "transliteration": "wa khawfi wa dhulli wa maskanati",
          "translation": "my fear, my humiliation, my neediness,"
        },
        {
          "arabic": "وَتَعْوِيذِي وَتَلْوِيذِي",
          "transliteration": "wa ta`widhi wa talwidhi",
          "translation": "my seeking Your protection, and my seeking Your refuge."
        },
        {
          "arabic": "يَا رَبِّ إِنِّي ضَعِيفٌ عَنْ طَلَبِ ٱلدُّنْيَا",
          "transliteration": "ya rabbi inni da`ifun `an talabi alddunya",
          "translation": "O my Lord, I am too weak to seek earnings in this world"
        },
        {
          "arabic": "وَأَنْتَ وَاسِعٌ كَرِيمٌ",
          "transliteration": "wa anta wasi`un karimun",
          "translation": "and You are Ample-giving and All-generous."
        },
        {
          "arabic": "أَسْأَلُكَ يَا رَبِّ بِقُوَّتِكَ عَلَىٰ ذٰلِكَ",
          "transliteration": "as'aluka ya rabbi biquwwatika `ala dhalika",
          "translation": "I beseech You, O my Lord, in the name of Your power over that,"
        },
        {
          "arabic": "وَقُدْرَتِكَ عَلَيْهِ",
          "transliteration": "wa qudratika `alayhi",
          "translation": "Your supremacy over that,"
        },
        {
          "arabic": "وَغِنَاكَ عَنْهُ",
          "transliteration": "wa ghinaka `anhu",
          "translation": "Your dispensing with that,"
        },
        {
          "arabic": "وَحَاجَتِي إِلَيْهِ",
          "transliteration": "wa hajati ilayhi",
          "translation": "and my urgent need for that"
        },
        {
          "arabic": "أَنْ تَرْزُقَنِي فِي عَامِي هٰذَا",
          "transliteration": "an tarzuqani fi `ami hadha",
          "translation": "to grant me sustenance in this year,"
        },
        {
          "arabic": "وَشَهْرِي هٰذَا",
          "transliteration": "wa shahri hadha",
          "translation": "in this month,"
        },
        {
          "arabic": "وَيَوْمِي هٰذَا",
          "transliteration": "wa yawmi hadha",
          "translation": "on this day,"
        },
        {
          "arabic": "وَسَاعَتِي هٰذِهِ",
          "transliteration": "wa sa`ati hadhihi",
          "translation": "at this hour—"
        },
        {
          "arabic": "رِزْقاً تُغْنِينِي بِهِ عَنْ تَكَلُّفِ مَا فِي أَيْدِي ٱلنَّاسِ",
          "transliteration": "rizqan tughnini bihi `an takallufi ma fi aydi alnnasi",
          "translation": "sustenance by which You may make me dispense with what the others possess,"
        },
        {
          "arabic": "مِنْ رِزْقِكَ ٱلْحَلاَلِ ٱلطَّيِّبِ",
          "transliteration": "min rizqika alhalali alttayyibi",
          "translation": "from Your sustenance, legal and nice."
        },
        {
          "arabic": "أَيْ رَبِّ مِنْكَ أَطْلُبُ",
          "transliteration": "ay rabbi minka atlubu",
          "translation": "O my Lord, from You do I ask,"
        },
        {
          "arabic": "وَإِلَيْكَ أَرْغَبُ",
          "transliteration": "wa ilayka arghabu",
          "translation": "for You do I desire,"
        },
        {
          "arabic": "وَإِيَّاكَ أَرْجُو",
          "transliteration": "wa iyyaka arju",
          "translation": "and for You do I hope;"
        },
        {
          "arabic": "وَأَنْتَ أَهْلُ ذٰلِكَ",
          "transliteration": "wa anta ahlu dhalika",
          "translation": "and You are the worthiest of being hoped."
        },
        {
          "arabic": "لاَ أَرْجُو غَيْرَكَ",
          "transliteration": "la arju ghayraka",
          "translation": "I hope for none but You"
        },
        {
          "arabic": "وَلاَ أَثِقُ إِلاَّ بِكَ",
          "transliteration": "wa la athiqu illa bika",
          "translation": "and I trust in none but You."
        },
        {
          "arabic": "يَا أَرْحَمَ ٱلرَّاحِمِينَ",
          "transliteration": "ya arhama alrrahimina",
          "translation": "O most Merciful of all those who show mercy!"
        },
        {
          "arabic": "أَيْ رَبِّ ظَلَمْتُ نَفْسِي",
          "transliteration": "ay rabbi zalamtu nafsi",
          "translation": "O my Lord, I have wronged myself;"
        },
        {
          "arabic": "فَٱغْفِرْ لِي وَٱرْحَمْنِي وَعَافِنِي",
          "transliteration": "faghfir li warhamni wa `afini",
          "translation": "so, (please do) forgive me, have mercy upon me, and grant me good health."
        },
        {
          "arabic": "يَا سَامِعَ كُلِّ صَوْتٍ",
          "transliteration": "ya sami`a kulli sawtin",
          "translation": "O Hearer of all sounds!"
        },
        {
          "arabic": "وَيَا جَامِعَ كُلِّ فَوْتٍ",
          "transliteration": "wa ya jami`a kulli fawtin",
          "translation": "O He Who takes precedence over everything that passes away!"
        },
        {
          "arabic": "وَيَا بَارِئَ ٱلنُّفُوسِ بَعْدَ ٱلْمَوْتِ",
          "transliteration": "wa ya bari'a alnnufusi ba`da almawti",
          "translation": "O Reviver of all souls after death!"
        },
        {
          "arabic": "يَا مَنْ لاَ تَغْشَاهُ ٱلظُّلُمَاتُ",
          "transliteration": "ya man la taghshahu alzzulumatu",
          "translation": "O He Whom is not screened by murk!"
        },
        {
          "arabic": "وَلاَ تَشْتَبِهُ عَلَيْهِ ٱلأَصْوَاتُ",
          "transliteration": "wa la tashtabihu `alayhi al-aswatu",
          "translation": "O He Whom is not made confused by sounds!"
        },
        {
          "arabic": "وَلاَ يَشْغَلُهُ شَيْءٌ عَنْ شَيْءٍ",
          "transliteration": "wa la yashghaluhu shay'un `an shay'in",
          "translation": "O He Whom is not engaged by something against another thing!"
        },
        {
          "arabic": "أَعْطِ مُحَمَّداً صَلَّىٰ ٱللَّهُ عَلَيْهِ وَآلِهِ أَفْضَلَ مَا سَأَلَكَ",
          "transliteration": "a`ti muhammadan salla allahu `alayhi wa alihi afdala ma sa'alaka",
          "translation": "(Please do) grant Muhammad—peace be upon him and his Household—the best of all that for which he has besought You,"
        },
        {
          "arabic": "وَأَفْضَلَ مَا سُئِلْتَ لَه",
          "transliteration": "wa afdala ma su'ilta lahu",
          "translation": "the best of all that which has been asked from You for him,"
        },
        {
          "arabic": "وَأَفْضَلَ مَا أَنْتَ مَسْؤُولٌ لَهُ إِلَىٰ يَوْمِ ٱلْقِيَامَةِ",
          "transliteration": "wa afdala ma anta mas'ulun lahu ila yawmi alqiyamati",
          "translation": "and the best all that which You shall be asked for him up to the Resurrection Day;"
        },
        {
          "arabic": "وَهَبْ لِيَ ٱلْعَافِيَةَ حَتَّىٰ تُهَنِّئَنِي ٱلْمَعِيشَةَ",
          "transliteration": "wa hab liya al`afiyata hatta tuhanni'ani alma`ishata",
          "translation": "and grant me good health so that I may enjoy my life,"
        },
        {
          "arabic": "وَٱخْتِمْ لِي بِخَيْرٍ حَتَّىٰ لاَ تَضُرَّنِي ٱلذُّنُوبُ",
          "transliteration": "wakhtim li bikhayrin hatta la tadurrani aldhdhunubu",
          "translation": "an end up my life with a happy end so that my sins may not injure me."
        },
        {
          "arabic": "اَللَّهُمَّ رَضِّنِي بِمَا قَسَمْتَ لِي حَتَّىٰ لاَ أَسْأَلَ أَحَداً شَيْئاً",
          "transliteration": "allahumma raddini bima qasamta li hatta la as'ala ahadan shay'an",
          "translation": "O Allah, (please do) make me satisfied with that which You have decided for me so that I will not ask anyone else for anything."
        },
        {
          "arabic": "اَللَّهُمَّ صَلِّ عَلَىٰ مُحَمَّدٍ وَآلِ مُحَمَّدٍ",
          "transliteration": "allahumma salli `ala muhammadin wa ali muhammadin",
          "translation": "O Allah, (please do) send blessings to Muhammad and the Household of Muhammad,"
        },
        {
          "arabic": "وَٱفْتَحْ لِي خَزَائِنَ رَحْمَتِكَ",
          "transliteration": "waftah li khaza'ina rahmatika",
          "translation": "open to me the stores of Your mercy,"
        },
        {
          "arabic": "وَٱرْحَمْنِي رَحْمَةً لاَ تُعَذِّبُنِي بَعْدَهَا أَبَداً فِي ٱلدُّنْيَا وَٱلآخِرَةِ",
          "transliteration": "warhamni rahmatan la tu`adhdhibuni ba`daha abadan fi alddunya wal-akhirati",
          "translation": "cover me with mercy from You owing to which You will not punish me neither in this world nor in the Hereafter,"
        },
        {
          "arabic": "وَٱرْزُقْنِي مِنْ فَضْلِكَ ٱلْوَاسِعِ رِزْقاً حَلاَلاً طَيِّباً",
          "transliteration": "warzuqni min fadlika alwasi`i rizqan halalan tayyiban",
          "translation": "grant me legal and pleasant sustenance from Your limitless favor"
        },
        {
          "arabic": "لاَ تُفْقِرُنِي إِلَىٰ أَحَدٍ بَعْدَهُ سِوَاكَ",
          "transliteration": "la tufqiruni ila ahadin ba`dahu siwaka",
          "translation": "owing to which You will make me dispense with anyone other than You;"
        },
        {
          "arabic": "تَزِيدُنِي بِذٰلِكَ شُكْراً",
          "transliteration": "taziduni bidhalika shukran",
          "translation": "increasing my gratitude to You"
        },
        {
          "arabic": "وَإِلَيْكَ فَاقَةً وَفَقْراً",
          "transliteration": "wa ilayka faqatan wa faqran",
          "translation": "and my neediness and submission before You,"
        },
        {
          "arabic": "وَبِكَ عَمَّنْ سِوَاكَ غِنَىٰ وَتَعَفُّفاً",
          "transliteration": "wa bika `amman siwaka ghinan wa ta`affufan",
          "translation": "and increasing my dispensing with and doing without everyone save You."
        },
        {
          "arabic": "يَا مُحْسِنُ يَا مُجْمِلُ",
          "transliteration": "ya muhsinu ya mujmilu",
          "translation": "O All-benefactor! O All-donor!"
        },
        {
          "arabic": "يَا مُنْعِمُ يَا مُفْضِلُ",
          "transliteration": "ya mun`imu ya mufdilu",
          "translation": "O All-favorer! O All-liberal!"
        },
        {
          "arabic": "يَا مَلِيكُ يَا مُقْتَدِرُ",
          "transliteration": "ya maliku ya muqtadiru",
          "translation": "O All-omnipotent! O All-sovereign!"
        },
        {
          "arabic": "صَلِّ عَلَىٰ مُحَمَّدٍ وَآلِ مُحَمَّدٍ",
          "transliteration": "salli `ala muhammadin wa ali muhammadin",
          "translation": "(Please do) send blessings to Muhammad and the Household of Muhammad,"
        },
        {
          "arabic": "وَٱكْفِنِي ٱلْمُهِمَّ كُلَّهُ",
          "transliteration": "wakfini almuhimma kullahu",
          "translation": "and relieve me from all grievances,"
        },
        {
          "arabic": "وَٱقْضِ لِي بِٱلْحُسْنَىٰ",
          "transliteration": "waqdi li bilhusna",
          "translation": "decide the most excellent for me,"
        },
        {
          "arabic": "وَبَارِكْ لِي فِي جَمِيعِ أُمُورِي",
          "transliteration": "wa barik li fi jami`i umuri",
          "translation": "bless all my affairs,"
        },
        {
          "arabic": "وَٱقْضِ لِي جَمِيعَ حَوَائِجِي",
          "transliteration": "waqdi li jami`a hawa'iji",
          "translation": "and settle all my needs."
        },
        {
          "arabic": "اَللَّهُمَّ يَسِّرْ لِي مَا أَخَافُ تَعْسِيرَهُ",
          "transliteration": "allahumma yassir li ma akhafu ta`sirahu",
          "translation": "O Allah, (please do) make easy for me all that which I anticipate to be difficult,"
        },
        {
          "arabic": "فَإِنَّ تَيْسِيرَ مَا أَخَافُ تَعْسِيرَهُ عَلَيْكَ سَهْلٌ يَسِيرٌ",
          "transliteration": "fa'inna taysira ma akhafu ta`sirahu `alayka sahlun yasirun",
          "translation": "for it is quite easy for You to make easy for me that which I anticipate to be difficult."
        },
        {
          "arabic": "وَسَهِّلْ لِي مَا أَخَافُ حُزُونَتَهُ",
          "transliteration": "wa sahhil li ma akhafu huzunatahu",
          "translation": "(Please do) facilitate for me that I anticipate to be complicated,"
        },
        {
          "arabic": "وَنَفِّسْ عَنِّي مَا أَخَافُ ضِيقَهُ",
          "transliteration": "wa naffis `anni ma akhafu diqahu",
          "translation": "give vent to that which I anticipate to be narrow,"
        },
        {
          "arabic": "وَكُفَّ عَنِّي مَا أَخَافُ هَمَّهُ",
          "transliteration": "wa kuffa `anni ma akhafu hammahu",
          "translation": "save me from that which I anticipate to cause me distress,"
        },
        {
          "arabic": "وَٱصْرِفْ عَنِّي مَا أَخَافُ بَلِيَّتَهُ",
          "transliteration": "wasrif `anni ma akhafu baliyyatahu",
          "translation": "and guard me from that which I anticipate to cause me misfortune."
        },
        {
          "arabic": "يَا أَرْحَمَ ٱلرَّاحِمِينَ",
          "transliteration": "ya arhama alrrahimina",
          "translation": "O most Merciful of all those who show mercy!"
        },
        {
          "arabic": "اَللَّهُمَّ ٱمْلَأْ قَلْبِي حُبّاً لَكَ",
          "transliteration": "allahumma imla' qalbi hubban laka",
          "translation": "O Allah, (please do) fill in my heart with love for You,"
        },
        {
          "arabic": "وَخَشْيَةً مِنْكَ",
          "transliteration": "wa khashyatan minka",
          "translation": "fear from You,"
        },
        {
          "arabic": "وَتَصْدِيقاً لَكَ",
          "transliteration": "wa tasdiqan laka",
          "translation": "belief in You,"
        },
        {
          "arabic": "وَإِيـمَاناً بِكَ",
          "transliteration": "wa imanan bika",
          "translation": "faith in You,"
        },
        {
          "arabic": "وَفَرَقاً مِنْكَ",
          "transliteration": "wa faraqan minka",
          "translation": "dread from You,"
        },
        {
          "arabic": "وَشَوْقاً إِلَيْكَ",
          "transliteration": "wa shawqan ilayka",
          "translation": "and eagerness to You."
        },
        {
          "arabic": "يَا ذَا ٱلْجَلالِ وَٱلإِكْرَامِ",
          "transliteration": "ya dha aljalali wal-ikrami",
          "translation": "O Lord of Majesty and Honor!"
        },
        {
          "arabic": "اَللَّهُمَّ إِنَّ لَكَ حُقُوقاً فَتَصَدَّقْ بِهَا عَلَيَّ",
          "transliteration": "allahumma inna laka huquqan fatasaddaq biha `alayya",
          "translation": "O Allah, I owe You some rights; so, (please do) consider them alms and excuse me from their liabilities."
        },
        {
          "arabic": "وَلِلنَّاسِ قِبَلِي تَبِعَاتٌ فَتَحَمَّلْهَا عَنِّي",
          "transliteration": "wa lilnnasi qibali tabi`atun fatahammalha `anni",
          "translation": "I also owe people some responsibilities; so, (please do) release me from their charges."
        },
        {
          "arabic": "وَقَدْ أَوْجَبْتَ لِكُلِّ ضَيْفٍ قِرَىٰ",
          "transliteration": "wa qad awjabta likulli dayfin qiran",
          "translation": "You have instructed us to honor our guests,"
        },
        {
          "arabic": "وَأَنَا ضَيْفُكَ فَٱجْعَلْ قِرَايَ ٱللَّيْلَةَ ٱلْجَنَّةَ",
          "transliteration": "wa ana dayfuka faj`al qiraya allaylata aljannata",
          "translation": "and I am Your guest at this night; so, (please do) decide Paradise for me as honor at this night."
        },
        {
          "arabic": "يَا وَهَّابَ ٱلْجَنَّةِ",
          "transliteration": "ya wahhaba aljannati",
          "translation": "O Grantor of Paradise!"
        },
        {
          "arabic": "يَا وَهَّابَ ٱلْمَغْفِرَةِ",
          "transliteration": "ya wahhaba almaghfirati",
          "translation": "O Grantor of forgiveness!"
        },
        {
          "arabic": "وَلاَ حَوْلَ وَلاَ قُوَّةَ إِلاَّ بِكَ",
          "transliteration": "wa la hawla wa la quwwata illa bika",
          "translation": "There is no power nor might save with You."
        }
      ],
      "audio": "https://mp3.duas.org/Ramdhan%20Special/Sahar-3Ya%20uddate.mp3",
      "youtube": "https://youtu.be/N985AI5XXP8",
      "reference": "",
      "tags": [],
      "meta": {
        "featured": false,
        "hasTiming": false,
        "type": "Supplication",
        "collection": "",
        "purpose": [],
        "personalities": [],
        "timing": {
          "days": [],
          "times": [
            "Fajr"
          ],
          "events": [],
          "dates": [
            {
              "month": "Ramadan"
            }
          ]
        },
        "locations": [],
        "pilgrimage": []
      }
    }
  ],
  "meta": {
    "featured": false,
    "hasTiming": false,
    "type": "Supplication",
    "collection": "",
    "purpose": [],
    "personalities": [],
    "timing": {
      "days": [],
      "times": [
        "Fajr"
      ],
      "events": [],
      "dates": [
        {
          "month": "Ramadan"
        }
      ]
    },
    "locations": [],
    "pilgrimage": []
  },
  "_index_meta": {
    "id": "ramadan-sahar-dua-ya-uddati",
    "title": "Dua Ya Uddati - Dua for sahar time (commencing the fast)",
    "description": "",
    "tags": [],
    "meta": {
      "featured": false,
      "hasTiming": false,
      "type": "Supplication",
      "collection": "",
      "purpose": [],
      "personalities": [],
      "timing": {
        "days": [],
        "times": [
          "Fajr"
        ],
        "events": [],
        "dates": [
          {
            "month": "Ramadan"
          }
        ]
      },
      "locations": [],
      "pilgrimage": []
    }
  }
}